djwebdapp
djwebdapp_ethereum
djwebdapp_example
djwebdapp_example_ethereum
djwebdapp_example_tezos
djwebdapp_fa2
djwebdapp_multisig
djwebdapp_rest_framework
djwebdapp_tezos
