Metadata-Version: 2.4
Name: djwebdapp
Version: 0.6.17
Home-page: https://yourlabs.io/oss/djwebdapp
Author: James Pic
Author-email: jamespic@gmail.com
License: MIT
Keywords: cli
Requires-Python: >=3.8
License-File: LICENSE
Requires-Dist: django-model-utils
Requires-Dist: djfernet>=0.8.1
Requires-Dist: django-picklefield>=3.0.1
Requires-Dist: networkx==2.8.8
Requires-Dist: mnemonic
Provides-Extra: test
Requires-Dist: django; extra == "test"
Requires-Dist: djangorestframework; extra == "test"
Requires-Dist: pytest; extra == "test"
Requires-Dist: pytest-cov; extra == "test"
Requires-Dist: pytest-django; extra == "test"
Requires-Dist: web3>=7.3.0; extra == "test"
Provides-Extra: ethereum
Requires-Dist: web3>=7.3.0; extra == "ethereum"
Provides-Extra: tezos
Requires-Dist: pytezos>3.4; extra == "tezos"
Requires-Dist: pymich>=0.9.8; extra == "tezos"
Provides-Extra: binary
Requires-Dist: pysodium; extra == "binary"
Requires-Dist: secp256k1; extra == "binary"
Requires-Dist: fastecdsa; extra == "binary"
Provides-Extra: all
Requires-Dist: django; extra == "all"
Requires-Dist: djangorestframework; extra == "all"
Requires-Dist: pytest; extra == "all"
Requires-Dist: pytest-cov; extra == "all"
Requires-Dist: pytest-django; extra == "all"
Requires-Dist: web3>=7.3.0; extra == "all"
Requires-Dist: web3>=7.3.0; extra == "all"
Requires-Dist: pytezos>3.4; extra == "all"
Requires-Dist: pymich>=0.9.8; extra == "all"
Requires-Dist: django; extra == "all"
Requires-Dist: djangorestframework; extra == "all"
Requires-Dist: pytest; extra == "all"
Requires-Dist: pytest-cov; extra == "all"
Requires-Dist: pytest-django; extra == "all"
Requires-Dist: web3>=7.3.0; extra == "all"
Requires-Dist: web3>=7.3.0; extra == "all"
Requires-Dist: pytezos>3.4; extra == "all"
Requires-Dist: pymich>=0.9.8; extra == "all"
Dynamic: author
Dynamic: author-email
Dynamic: description
Dynamic: description-content-type
Dynamic: home-page
Dynamic: keywords
Dynamic: license
Dynamic: license-file
Dynamic: provides-extra
Dynamic: requires-dist
Dynamic: requires-python
